datacat/__init__.py
datacat/catalog_storage.py
datacat/serializers.py
datacatalog_storage-1.0.0.dist-info/licenses/LICENSE
datacatalog_storage-1.0.0.dist-info/METADATA
datacatalog_storage-1.0.0.dist-info/WHEEL
datacatalog_storage-1.0.0.dist-info/top_level.txt
datacatalog_storage-1.0.0.dist-info/RECORD
