Metadata-Version: 2.4
Name: datacatalog-storage
Version: 1.0.0
Summary: Catalog-based data storage system with pluggable serializers
Author-email: DataCat Team <datacat@example.com>
Maintainer-email: DataCat Team <datacat@example.com>
License-Expression: MIT
Project-URL: Homepage, https://github.com/papasaidfine/datacat
Project-URL: Repository, https://github.com/papasaidfine/datacat
Project-URL: Bug Reports, https://github.com/papasaidfine/datacat/issues
Project-URL: Documentation, https://github.com/papasaidfine/datacat#readme
Keywords: data,storage,serialization,catalog,numpy,scipy
Classifier: Development Status :: 4 - Beta
Classifier: Intended Audience :: Developers
Classifier: Intended Audience :: Science/Research
Classifier: Topic :: Software Development :: Libraries :: Python Modules
Classifier: Topic :: Scientific/Engineering
Classifier: Programming Language :: Python :: 3
Classifier: Programming Language :: Python :: 3.8
Classifier: Programming Language :: Python :: 3.9
Classifier: Programming Language :: Python :: 3.10
Classifier: Programming Language :: Python :: 3.11
Classifier: Programming Language :: Python :: 3.12
Classifier: Operating System :: OS Independent
Requires-Python: >=3.8
License-File: LICENSE
Requires-Dist: numpy>=1.20.0
Requires-Dist: scipy>=1.7.0
Requires-Dist: duckdb>=0.8.0
Provides-Extra: dev
Requires-Dist: pytest>=7.0.0; extra == "dev"
Requires-Dist: black>=22.0.0; extra == "dev"
Requires-Dist: flake8>=4.0.0; extra == "dev"
Dynamic: license-file
